purple_mri/__init__.py
purple_mri/__main__.py
purple_mri/scripts/create_mesh.sh
purple_mri/scripts/decimate_mesh.py
purple_mri/scripts/do_mni_txs.sh
purple_mri/scripts/make_fs_directories.sh
purple_mri/scripts/parcellation.sh
purple_mri/scripts/prepare_segm_files.sh
purple_mri/scripts/run_surface_pipeline.sh
purple_mri/scripts/topology_correction.sh
purple_mri-0.0.1.data/scripts/create_mesh.sh
purple_mri-0.0.1.data/scripts/decimate_mesh.py
purple_mri-0.0.1.data/scripts/do_mni_txs.sh
purple_mri-0.0.1.data/scripts/make_fs_directories.sh
purple_mri-0.0.1.data/scripts/parcellation.sh
purple_mri-0.0.1.data/scripts/prepare_segm_files.sh
purple_mri-0.0.1.data/scripts/run_surface_pipeline.sh
purple_mri-0.0.1.data/scripts/topology_correction.sh
purple_mri-0.0.1.dist-info/METADATA
purple_mri-0.0.1.dist-info/WHEEL
purple_mri-0.0.1.dist-info/top_level.txt
purple_mri-0.0.1.dist-info/RECORD
