Metadata-Version: 2.1
Name: purple_mri
Version: 0.0.1
Summary: purple_mri: Penn Utilities for Registration and ParcelLation of Ex vivo MRI
Author-email: Pulkit Khandelwal <kpulkit95@gmail.com>
Project-URL: Homepage, https://github.com/Pulkit-Khandelwal/purple_mri
Requires-Dist: numpy
Requires-Dist: torch
Requires-Dist: pykeops
Requires-Dist: pymeshlab
Requires-Dist: vtk
Requires-Dist: SimpleITK
Requires-Dist: geomloss
